{
  "tasks": [
    {
      "user": "user1",
      "status": "in-progress",
      "DueDate": "2024-09-13",
      "priority": "high",
      "Description": "This task is good",
      "id": "1"
    },
    {
      "id": "2",
      "user": "user2",
      "status": "Completed",
      "DueDate": "2024-09-19",
      "priority": "high",
      "Description": "This task needs immediate attention"
    },
    {
      "id": "3",
      "user": "user3",
      "status": "In progress",
      "DueDate": "2024-09-25",
      "priority": "medium",
      "Description": "Working on the project documentation"
    },
    {
      "id": "4",
      "user": "user4",
      "status": "Not started",
      "DueDate": "2024-09-30",
      "priority": "low",
      "Description": "Prepare for the team meeting"
    },
    {
      "id": "5",
      "user": "user5",
      "status": "Completed",
      "DueDate": "2024-09-15",
      "priority": "high",
      "Description": "Finish the UI redesign"
    },
    {
      "id": "6",
      "user": "user6",
      "status": "In progress",
      "DueDate": "2024-09-28",
      "priority": "medium",
      "Description": "Implement the new feature"
    },
    {
      "id": "7",
      "user": "user7",
      "status": "Not started",
      "DueDate": "2024-10-05",
      "priority": "normal",
      "Description": "Conduct a code review"
    },
    {
      "id": "8",
      "user": "user8",
      "status": "In progress",
      "DueDate": "2024-10-10",
      "priority": "high",
      "Description": "Optimize the database queries"
    },
    {
      "id": "9",
      "user": "user9",
      "status": "Not started",
      "DueDate": "2024-10-15",
      "priority": "low",
      "Description": "Update the API documentation"
    },
    {
      "id": "10",
      "user": "user10",
      "status": "Completed",
      "DueDate": "2024-09-20",
      "priority": "medium",
      "Description": "Deploy the application to production"
    },
    {
      "id": "5f9c",
      "user": "user6",
      "status": "Not started ",
      "DueDate": "2024-09-12",
      "priority": "normal",
      "Description": "the task is good "
    },
    {
      "id": "cce1"
    },
    {
      "id": "6f16",
      "user": "user10",
      "status": "in-progress",
      "DueDate": "2024-09-12",
      "priority": "normal",
      "Description": "need to improve"
    }
  ]
}